OpenwrtZhinengZidongToumingFanqiangLuyouqiJiaocheng/README.md
OpenwrtZhinengZidongToumingFanqiangLuyouqiJiaocheng/__init__.py
OpenwrtZhinengZidongToumingFanqiangLuyouqiJiaocheng/__main__.py
OpenwrtZhinengZidongToumingFanqiangLuyouqiJiaocheng/file.epub
OpenwrtZhinengZidongToumingFanqiangLuyouqiJiaocheng/index.html
OpenwrtZhinengZidongToumingFanqiangLuyouqiJiaocheng/css/__init__.py
OpenwrtZhinengZidongToumingFanqiangLuyouqiJiaocheng/css/annotations.css
OpenwrtZhinengZidongToumingFanqiangLuyouqiJiaocheng/css/main.css
OpenwrtZhinengZidongToumingFanqiangLuyouqiJiaocheng/css/normalize.css
OpenwrtZhinengZidongToumingFanqiangLuyouqiJiaocheng/css/popup.css
OpenwrtZhinengZidongToumingFanqiangLuyouqiJiaocheng/font/__init__.py
OpenwrtZhinengZidongToumingFanqiangLuyouqiJiaocheng/font/fontello.eot
OpenwrtZhinengZidongToumingFanqiangLuyouqiJiaocheng/font/fontello.svg
OpenwrtZhinengZidongToumingFanqiangLuyouqiJiaocheng/font/fontello.ttf
OpenwrtZhinengZidongToumingFanqiangLuyouqiJiaocheng/font/fontello.woff
OpenwrtZhinengZidongToumingFanqiangLuyouqiJiaocheng/img/__init__.py
OpenwrtZhinengZidongToumingFanqiangLuyouqiJiaocheng/img/annotator-glyph-sprite.png
OpenwrtZhinengZidongToumingFanqiangLuyouqiJiaocheng/img/annotator-icon-sprite.png
OpenwrtZhinengZidongToumingFanqiangLuyouqiJiaocheng/img/apple-touch-icon.png
OpenwrtZhinengZidongToumingFanqiangLuyouqiJiaocheng/img/cancelfullscreen.png
OpenwrtZhinengZidongToumingFanqiangLuyouqiJiaocheng/img/close.png
OpenwrtZhinengZidongToumingFanqiangLuyouqiJiaocheng/img/fullscreen.png
OpenwrtZhinengZidongToumingFanqiangLuyouqiJiaocheng/img/loader.gif
OpenwrtZhinengZidongToumingFanqiangLuyouqiJiaocheng/img/menu-icon.png
OpenwrtZhinengZidongToumingFanqiangLuyouqiJiaocheng/img/save.png
OpenwrtZhinengZidongToumingFanqiangLuyouqiJiaocheng/img/saved.png
OpenwrtZhinengZidongToumingFanqiangLuyouqiJiaocheng/img/settings-s.png
OpenwrtZhinengZidongToumingFanqiangLuyouqiJiaocheng/img/settings.png
openwrt_zhineng_zidong_touming_fanqiang_luyouqi_jiaocheng-2024.3.1.0.dist-info/METADATA
openwrt_zhineng_zidong_touming_fanqiang_luyouqi_jiaocheng-2024.3.1.0.dist-info/WHEEL
openwrt_zhineng_zidong_touming_fanqiang_luyouqi_jiaocheng-2024.3.1.0.dist-info/entry_points.txt
openwrt_zhineng_zidong_touming_fanqiang_luyouqi_jiaocheng-2024.3.1.0.dist-info/top_level.txt
openwrt_zhineng_zidong_touming_fanqiang_luyouqi_jiaocheng-2024.3.1.0.dist-info/RECORD
